chatms_plugin/__init__.py
chatms_plugin/config.py
chatms_plugin/exceptions.py
chatms_plugin/api/__init__.py
chatms_plugin/api/django.py
chatms_plugin/api/middlewares.py
chatms_plugin/api/rest.py
chatms_plugin/api/websocket.py
chatms_plugin/core/__init__.py
chatms_plugin/core/analytics.py
chatms_plugin/core/chat_system.py
chatms_plugin/core/connection.py
chatms_plugin/core/security.py
chatms_plugin/database/__init__.py
chatms_plugin/database/base.py
chatms_plugin/database/mongodb.py
chatms_plugin/database/mongodb_base.py
chatms_plugin/database/mongodb_chat.py
chatms_plugin/database/mongodb_message.py
chatms_plugin/database/mongodb_user.py
chatms_plugin/database/postgresql.py
chatms_plugin/models/__init__.py
chatms_plugin/models/base.py
chatms_plugin/models/chat.py
chatms_plugin/models/message.py
chatms_plugin/models/user.py
chatms_plugin/notifications/__init__.py
chatms_plugin/notifications/apns.py
chatms_plugin/notifications/base.py
chatms_plugin/notifications/email.py
chatms_plugin/notifications/fcm.py
chatms_plugin/storage/__init__.py
chatms_plugin/storage/azure.py
chatms_plugin/storage/base.py
chatms_plugin/storage/gcp.py
chatms_plugin/storage/local.py
chatms_plugin/storage/s3.py
chatms_plugin/utils/__init__.py
chatms_plugin/utils/encryption.py
chatms_plugin/utils/file_processing.py
chatms_plugin/utils/rate_limiting.py
chatms_plugin/utils/validation.py
chatms_plugin-0.1.0.dist-info/licenses/LICENSE
tests/__init__.py
tests/conftest.py
tests/lightweight_mocks.py
tests/mocks.py
tests/test_chat_system.py
tests/test_database.py
tests/test_optimized.py
tests/test_security.py
tests/test_storage.py
tests/test_websocket.py
chatms_plugin-0.1.0.dist-info/METADATA
chatms_plugin-0.1.0.dist-info/WHEEL
chatms_plugin-0.1.0.dist-info/top_level.txt
chatms_plugin-0.1.0.dist-info/RECORD
