Metadata-Version: 2.4
Name: chatms-plugin
Version: 0.1.0
Summary: A comprehensive chat messaging system plugin for Python applications
Author-email: kabhishek <developer@kabhishek18.com>
License: MIT
Project-URL: Homepage, https://github.com/Kabhishek18/chatms-plugin
Project-URL: Bug Tracker, https://github.com/Kabhishek18/chatms-plugin/issues
Classifier: Programming Language :: Python :: 3
Classifier: Programming Language :: Python :: 3.9
Classifier: Programming Language :: Python :: 3.10
Classifier: License :: OSI Approved :: MIT License
Classifier: Operating System :: OS Independent
Classifier: Development Status :: 4 - Beta
Classifier: Intended Audience :: Developers
Classifier: Topic :: Communications :: Chat
Requires-Python: >=3.9
License-File: LICENSE
Requires-Dist: fastapi>=0.68.0
Requires-Dist: uvicorn>=0.15.0
Requires-Dist: websockets>=10.0
Requires-Dist: sqlalchemy>=1.4.0
Requires-Dist: motor>=2.5.0
Requires-Dist: pydantic>=1.8.0
Requires-Dist: python-jose>=3.3.0
Requires-Dist: passlib[bcrypt]>=1.7.4
Requires-Dist: python-multipart>=0.0.5
Requires-Dist: aioredis>=2.0.0
Requires-Dist: python-dotenv>=0.19.0
Requires-Dist: boto3>=1.18.0
Requires-Dist: google-cloud-storage>=1.42.0
Requires-Dist: azure-storage-blob>=12.8.0
Requires-Dist: firebase-admin>=5.0.0
Requires-Dist: aiofiles>=0.7.0
Provides-Extra: dev
Requires-Dist: pytest>=6.2.5; extra == "dev"
Requires-Dist: pytest-asyncio>=0.16.0; extra == "dev"
Requires-Dist: black>=21.7b0; extra == "dev"
Requires-Dist: isort>=5.9.3; extra == "dev"
Requires-Dist: mypy>=0.910; extra == "dev"
Requires-Dist: flake8>=3.9.2; extra == "dev"
Requires-Dist: pre-commit>=2.14.0; extra == "dev"
Requires-Dist: locust>=2.2.1; extra == "dev"
Dynamic: license-file
